sivalibrary/__init__.py
sivalibrary/evenodd.py
sivalibrary-0.1.dist-info/METADATA
sivalibrary-0.1.dist-info/WHEEL
sivalibrary-0.1.dist-info/top_level.txt
sivalibrary-0.1.dist-info/RECORD
