Metadata-Version: 2.4
Name: sivalibrary
Version: 0.1
Summary: Even or Odd identifies
Dynamic: summary
